[
  {
    "id": 1,
    "text": "49,091",
    "confidence": 0.9358323216438293,
    "quad": {
      "x1": 594.0,
      "y1": 809.0,
      "x2": 683.0,
      "y2": 806.0,
      "x3": 685.0,
      "y3": 846.0,
      "x4": 595.0,
      "y4": 850.0
    },
    "box": [
      [
        594.0,
        809.0
      ],
      [
        683.0,
        806.0
      ],
      [
        685.0,
        846.0
      ],
      [
        595.0,
        850.0
      ]
    ],
    "x_center": 639.25,
    "y_center": 827.75
  },
  {
    "id": 0,
    "text": "Kupon 13",
    "confidence": 0.9463053345680237,
    "quad": {
      "x1": 116.0,
      "y1": 818.0,
      "x2": 226.0,
      "y2": 815.0,
      "x3": 227.0,
      "y3": 854.0,
      "x4": 117.0,
      "y4": 858.0
    },
    "box": [
      [
        116.0,
        818.0
      ],
      [
        226.0,
        815.0
      ],
      [
        227.0,
        854.0
      ],
      [
        117.0,
        858.0
      ]
    ],
    "x_center": 171.5,
    "y_center": 836.25
  },
  {
    "id": 2,
    "text": "49,091",
    "confidence": 0.9398579597473145,
    "quad": {
      "x1": 599.0,
      "y1": 890.0,
      "x2": 690.0,
      "y2": 887.0,
      "x3": 692.0,
      "y3": 926.0,
      "x4": 600.0,
      "y4": 929.0
    },
    "box": [
      [
        599.0,
        890.0
      ],
      [
        690.0,
        887.0
      ],
      [
        692.0,
        926.0
      ],
      [
        600.0,
        929.0
      ]
    ],
    "x_center": 645.25,
    "y_center": 908.0
  },
  {
    "id": 4,
    "text": "4,909",
    "confidence": 0.942594051361084,
    "quad": {
      "x1": 612.0,
      "y1": 931.0,
      "x2": 694.0,
      "y2": 925.0,
      "x3": 698.0,
      "y3": 970.0,
      "x4": 615.0,
      "y4": 976.0
    },
    "box": [
      [
        612.0,
        931.0
      ],
      [
        694.0,
        925.0
      ],
      [
        698.0,
        970.0
      ],
      [
        615.0,
        976.0
      ]
    ],
    "x_center": 654.75,
    "y_center": 950.5
  },
  {
    "id": 3,
    "text": "P01(10%)",
    "confidence": 0.7826033234596252,
    "quad": {
      "x1": 113.0,
      "y1": 938.0,
      "x2": 234.0,
      "y2": 938.0,
      "x3": 234.0,
      "y3": 972.0,
      "x4": 113.0,
      "y4": 972.0
    },
    "box": [
      [
        113.0,
        938.0
      ],
      [
        234.0,
        938.0
      ],
      [
        234.0,
        972.0
      ],
      [
        113.0,
        972.0
      ]
    ],
    "x_center": 173.5,
    "y_center": 955.0
  },
  {
    "id": 6,
    "text": "54,000",
    "confidence": 0.9727739691734314,
    "quad": {
      "x1": 606.0,
      "y1": 1014.0,
      "x2": 700.0,
      "y2": 1011.0,
      "x3": 701.0,
      "y3": 1051.0,
      "x4": 607.0,
      "y4": 1055.0
    },
    "box": [
      [
        606.0,
        1014.0
      ],
      [
        700.0,
        1011.0
      ],
      [
        701.0,
        1051.0
      ],
      [
        607.0,
        1055.0
      ]
    ],
    "x_center": 653.5,
    "y_center": 1032.75
  },
  {
    "id": 5,
    "text": "Dine In Total",
    "confidence": 0.9648792743682861,
    "quad": {
      "x1": 108.0,
      "y1": 1016.0,
      "x2": 289.0,
      "y2": 1024.0,
      "x3": 288.0,
      "y3": 1060.0,
      "x4": 106.0,
      "y4": 1053.0
    },
    "box": [
      [
        108.0,
        1016.0
      ],
      [
        289.0,
        1024.0
      ],
      [
        288.0,
        1060.0
      ],
      [
        106.0,
        1053.0
      ]
    ],
    "x_center": 197.75,
    "y_center": 1038.25
  },
  {
    "id": 8,
    "text": "Rp.100,000",
    "confidence": 0.9458391070365906,
    "quad": {
      "x1": 554.0,
      "y1": 1102.0,
      "x2": 704.0,
      "y2": 1097.0,
      "x3": 705.0,
      "y3": 1136.0,
      "x4": 556.0,
      "y4": 1141.0
    },
    "box": [
      [
        554.0,
        1102.0
      ],
      [
        704.0,
        1097.0
      ],
      [
        705.0,
        1136.0
      ],
      [
        556.0,
        1141.0
      ]
    ],
    "x_center": 629.75,
    "y_center": 1119.0
  },
  {
    "id": 7,
    "text": "Cash",
    "confidence": 0.993598997592926,
    "quad": {
      "x1": 103.0,
      "y1": 1103.0,
      "x2": 170.0,
      "y2": 1103.0,
      "x3": 170.0,
      "y3": 1139.0,
      "x4": 103.0,
      "y4": 1139.0
    },
    "box": [
      [
        103.0,
        1103.0
      ],
      [
        170.0,
        1103.0
      ],
      [
        170.0,
        1139.0
      ],
      [
        103.0,
        1139.0
      ]
    ],
    "x_center": 136.5,
    "y_center": 1121.0
  },
  {
    "id": 9,
    "text": "Change",
    "confidence": 0.9982993006706238,
    "quad": {
      "x1": 101.0,
      "y1": 1184.0,
      "x2": 194.0,
      "y2": 1191.0,
      "x3": 191.0,
      "y3": 1232.0,
      "x4": 98.0,
      "y4": 1225.0
    },
    "box": [
      [
        101.0,
        1184.0
      ],
      [
        194.0,
        1191.0
      ],
      [
        191.0,
        1232.0
      ],
      [
        98.0,
        1225.0
      ]
    ],
    "x_center": 146.0,
    "y_center": 1208.0
  },
  {
    "id": 10,
    "text": "46,000",
    "confidence": 0.9459114074707031,
    "quad": {
      "x1": 616.0,
      "y1": 1188.0,
      "x2": 714.0,
      "y2": 1185.0,
      "x3": 716.0,
      "y3": 1228.0,
      "x4": 618.0,
      "y4": 1232.0
    },
    "box": [
      [
        616.0,
        1188.0
      ],
      [
        714.0,
        1185.0
      ],
      [
        716.0,
        1228.0
      ],
      [
        618.0,
        1232.0
      ]
    ],
    "x_center": 666.0,
    "y_center": 1208.25
  }
]