[
  {
    "id": 0,
    "text": "TOAST BREAD",
    "confidence": 0.9671856164932251,
    "quad": {
      "x1": 270.0,
      "y1": 1522.0,
      "x2": 704.0,
      "y2": 1541.0,
      "x3": 700.0,
      "y3": 1631.0,
      "x4": 266.0,
      "y4": 1612.0
    },
    "box": [
      [
        270.0,
        1522.0
      ],
      [
        704.0,
        1541.0
      ],
      [
        700.0,
        1631.0
      ],
      [
        266.0,
        1612.0
      ]
    ],
    "x_center": 485.0,
    "y_center": 1576.5
  },
  {
    "id": 1,
    "text": "28,000",
    "confidence": 0.9436786770820618,
    "quad": {
      "x1": 1392.0,
      "y1": 1610.0,
      "x2": 1630.0,
      "y2": 1594.0,
      "x3": 1637.0,
      "y3": 1688.0,
      "x4": 1398.0,
      "y4": 1704.0
    },
    "box": [
      [
        1392.0,
        1610.0
      ],
      [
        1630.0,
        1594.0
      ],
      [
        1637.0,
        1688.0
      ],
      [
        1398.0,
        1704.0
      ]
    ],
    "x_center": 1514.25,
    "y_center": 1649.0
  },
  {
    "id": 2,
    "text": "28,000",
    "confidence": 0.9655894637107849,
    "quad": {
      "x1": 986.0,
      "y1": 1631.0,
      "x2": 1225.0,
      "y2": 1620.0,
      "x3": 1230.0,
      "y3": 1714.0,
      "x4": 990.0,
      "y4": 1725.0
    },
    "box": [
      [
        986.0,
        1631.0
      ],
      [
        1225.0,
        1620.0
      ],
      [
        1230.0,
        1714.0
      ],
      [
        990.0,
        1725.0
      ]
    ],
    "x_center": 1107.75,
    "y_center": 1672.5
  },
  {
    "id": 3,
    "text": "1",
    "confidence": 0.790611982345581,
    "quad": {
      "x1": 577.0,
      "y1": 1652.0,
      "x2": 621.0,
      "y2": 1641.0,
      "x3": 634.0,
      "y3": 1694.0,
      "x4": 590.0,
      "y4": 1705.0
    },
    "box": [
      [
        577.0,
        1652.0
      ],
      [
        621.0,
        1641.0
      ],
      [
        634.0,
        1694.0
      ],
      [
        590.0,
        1705.0
      ]
    ],
    "x_center": 605.5,
    "y_center": 1673.0
  },
  {
    "id": 5,
    "text": "28,000",
    "confidence": 0.9434170722961426,
    "quad": {
      "x1": 1171.0,
      "y1": 1810.0,
      "x2": 1634.0,
      "y2": 1790.0,
      "x3": 1641.0,
      "y3": 1948.0,
      "x4": 1178.0,
      "y4": 1969.0
    },
    "box": [
      [
        1171.0,
        1810.0
      ],
      [
        1634.0,
        1790.0
      ],
      [
        1641.0,
        1948.0
      ],
      [
        1178.0,
        1969.0
      ]
    ],
    "x_center": 1406.0,
    "y_center": 1879.25
  },
  {
    "id": 4,
    "text": "TOTAL",
    "confidence": 0.9983831644058228,
    "quad": {
      "x1": 546.0,
      "y1": 1818.0,
      "x2": 923.0,
      "y2": 1818.0,
      "x3": 923.0,
      "y3": 1971.0,
      "x4": 546.0,
      "y4": 1971.0
    },
    "box": [
      [
        546.0,
        1818.0
      ],
      [
        923.0,
        1818.0
      ],
      [
        923.0,
        1971.0
      ],
      [
        546.0,
        1971.0
      ]
    ],
    "x_center": 734.5,
    "y_center": 1894.5
  },
  {
    "id": 6,
    "text": "28,000",
    "confidence": 0.9671795964241028,
    "quad": {
      "x1": 1401.0,
      "y1": 1951.0,
      "x2": 1640.0,
      "y2": 1940.0,
      "x3": 1645.0,
      "y3": 2038.0,
      "x4": 1405.0,
      "y4": 2049.0
    },
    "box": [
      [
        1401.0,
        1951.0
      ],
      [
        1640.0,
        1940.0
      ],
      [
        1645.0,
        2038.0
      ],
      [
        1405.0,
        2049.0
      ]
    ],
    "x_center": 1522.75,
    "y_center": 1994.5
  },
  {
    "id": 7,
    "text": "CASH",
    "confidence": 0.9981707334518433,
    "quad": {
      "x1": 551.0,
      "y1": 1971.0,
      "x2": 716.0,
      "y2": 1971.0,
      "x3": 716.0,
      "y3": 2052.0,
      "x4": 551.0,
      "y4": 2052.0
    },
    "box": [
      [
        551.0,
        1971.0
      ],
      [
        716.0,
        1971.0
      ],
      [
        716.0,
        2052.0
      ],
      [
        551.0,
        2052.0
      ]
    ],
    "x_center": 633.5,
    "y_center": 2011.5
  },
  {
    "id": 8,
    "text": "0",
    "confidence": 0.922152042388916,
    "quad": {
      "x1": 1546.0,
      "y1": 2048.0,
      "x2": 1648.0,
      "y2": 2048.0,
      "x3": 1648.0,
      "y3": 2197.0,
      "x4": 1546.0,
      "y4": 2197.0
    },
    "box": [
      [
        1546.0,
        2048.0
      ],
      [
        1648.0,
        2048.0
      ],
      [
        1648.0,
        2197.0
      ],
      [
        1546.0,
        2197.0
      ]
    ],
    "x_center": 1597.0,
    "y_center": 2122.5
  },
  {
    "id": 9,
    "text": "CHANGE",
    "confidence": 0.9981814026832581,
    "quad": {
      "x1": 541.0,
      "y1": 2062.0,
      "x2": 1010.0,
      "y2": 2051.0,
      "x3": 1013.0,
      "y3": 2205.0,
      "x4": 544.0,
      "y4": 2215.0
    },
    "box": [
      [
        541.0,
        2062.0
      ],
      [
        1010.0,
        2051.0
      ],
      [
        1013.0,
        2205.0
      ],
      [
        544.0,
        2215.0
      ]
    ],
    "x_center": 777.0,
    "y_center": 2133.25
  }
]