[
  {
    "id": 0,
    "text": "9,000",
    "confidence": 0.983738899230957,
    "quad": {
      "x1": 1726.0,
      "y1": 1674.0,
      "x2": 1962.0,
      "y2": 1663.0,
      "x3": 1967.0,
      "y3": 1769.0,
      "x4": 1732.0,
      "y4": 1781.0
    },
    "box": [
      [
        1726.0,
        1674.0
      ],
      [
        1962.0,
        1663.0
      ],
      [
        1967.0,
        1769.0
      ],
      [
        1732.0,
        1781.0
      ]
    ],
    "x_center": 1846.75,
    "y_center": 1721.75
  },
  {
    "id": 1,
    "text": "1 REDBEAN BREAD",
    "confidence": 0.9318487048149109,
    "quad": {
      "x1": 478.0,
      "y1": 1703.0,
      "x2": 1113.0,
      "y2": 1693.0,
      "x3": 1114.0,
      "y3": 1783.0,
      "x4": 479.0,
      "y4": 1792.0
    },
    "box": [
      [
        478.0,
        1703.0
      ],
      [
        1113.0,
        1693.0
      ],
      [
        1114.0,
        1783.0
      ],
      [
        479.0,
        1792.0
      ]
    ],
    "x_center": 796.0,
    "y_center": 1742.75
  },
  {
    "id": 2,
    "text": "12,000",
    "confidence": 0.9491848349571228,
    "quad": {
      "x1": 1705.0,
      "y1": 1776.0,
      "x2": 1966.0,
      "y2": 1765.0,
      "x3": 1971.0,
      "y3": 1867.0,
      "x4": 1710.0,
      "y4": 1879.0
    },
    "box": [
      [
        1705.0,
        1776.0
      ],
      [
        1966.0,
        1765.0
      ],
      [
        1971.0,
        1867.0
      ],
      [
        1710.0,
        1879.0
      ]
    ],
    "x_center": 1838.0,
    "y_center": 1821.75
  },
  {
    "id": 3,
    "text": "1 FRANKFRUT SAUSAGE ROLL",
    "confidence": 0.9261950850486755,
    "quad": {
      "x1": 482.0,
      "y1": 1810.0,
      "x2": 1464.0,
      "y2": 1791.0,
      "x3": 1466.0,
      "y3": 1877.0,
      "x4": 484.0,
      "y4": 1895.0
    },
    "box": [
      [
        482.0,
        1810.0
      ],
      [
        1464.0,
        1791.0
      ],
      [
        1466.0,
        1877.0
      ],
      [
        484.0,
        1895.0
      ]
    ],
    "x_center": 974.0,
    "y_center": 1843.25
  },
  {
    "id": 4,
    "text": "21,000",
    "confidence": 0.9377680420875549,
    "quad": {
      "x1": 1463.0,
      "y1": 1990.0,
      "x2": 1964.0,
      "y2": 1964.0,
      "x3": 1972.0,
      "y3": 2136.0,
      "x4": 1471.0,
      "y4": 2161.0
    },
    "box": [
      [
        1463.0,
        1990.0
      ],
      [
        1964.0,
        1964.0
      ],
      [
        1972.0,
        2136.0
      ],
      [
        1471.0,
        2161.0
      ]
    ],
    "x_center": 1717.5,
    "y_center": 2062.75
  },
  {
    "id": 5,
    "text": "TOTAL",
    "confidence": 0.9986602067947388,
    "quad": {
      "x1": 576.0,
      "y1": 2005.0,
      "x2": 995.0,
      "y2": 2005.0,
      "x3": 995.0,
      "y3": 2163.0,
      "x4": 576.0,
      "y4": 2163.0
    },
    "box": [
      [
        576.0,
        2005.0
      ],
      [
        995.0,
        2005.0
      ],
      [
        995.0,
        2163.0
      ],
      [
        576.0,
        2163.0
      ]
    ],
    "x_center": 785.5,
    "y_center": 2084.0
  },
  {
    "id": 6,
    "text": "50,000",
    "confidence": 0.9488976001739502,
    "quad": {
      "x1": 1714.0,
      "y1": 2139.0,
      "x2": 1971.0,
      "y2": 2128.0,
      "x3": 1975.0,
      "y3": 2222.0,
      "x4": 1718.0,
      "y4": 2233.0
    },
    "box": [
      [
        1714.0,
        2139.0
      ],
      [
        1971.0,
        2128.0
      ],
      [
        1975.0,
        2222.0
      ],
      [
        1718.0,
        2233.0
      ]
    ],
    "x_center": 1844.5,
    "y_center": 2180.5
  },
  {
    "id": 7,
    "text": "CASH",
    "confidence": 0.9980579614639282,
    "quad": {
      "x1": 576.0,
      "y1": 2172.0,
      "x2": 767.0,
      "y2": 2172.0,
      "x3": 767.0,
      "y3": 2266.0,
      "x4": 576.0,
      "y4": 2266.0
    },
    "box": [
      [
        576.0,
        2172.0
      ],
      [
        767.0,
        2172.0
      ],
      [
        767.0,
        2266.0
      ],
      [
        576.0,
        2266.0
      ]
    ],
    "x_center": 671.5,
    "y_center": 2219.0
  },
  {
    "id": 8,
    "text": "29,000",
    "confidence": 0.9494964480400085,
    "quad": {
      "x1": 1477.0,
      "y1": 2245.0,
      "x2": 1983.0,
      "y2": 2230.0,
      "x3": 1988.0,
      "y3": 2401.0,
      "x4": 1482.0,
      "y4": 2416.0
    },
    "box": [
      [
        1477.0,
        2245.0
      ],
      [
        1983.0,
        2230.0
      ],
      [
        1988.0,
        2401.0
      ],
      [
        1482.0,
        2416.0
      ]
    ],
    "x_center": 1732.5,
    "y_center": 2323.0
  },
  {
    "id": 9,
    "text": "CHANGE",
    "confidence": 0.9981505274772644,
    "quad": {
      "x1": 570.0,
      "y1": 2280.0,
      "x2": 1079.0,
      "y2": 2259.0,
      "x3": 1086.0,
      "y3": 2426.0,
      "x4": 577.0,
      "y4": 2447.0
    },
    "box": [
      [
        570.0,
        2280.0
      ],
      [
        1079.0,
        2259.0
      ],
      [
        1086.0,
        2426.0
      ],
      [
        577.0,
        2447.0
      ]
    ],
    "x_center": 828.0,
    "y_center": 2353.0
  }
]